minlog/__init__.py
minlog/_test.py
minlog/logger.py
minlog-0.6.0.dist-info/METADATA
minlog-0.6.0.dist-info/WHEEL
minlog-0.6.0.dist-info/RECORD
