Metadata-Version: 2.3
Name: minlog
Version: 0.6.0
Summary: a neat and simple minimalistic logging library for python
Author: redthing1
Author-email: redthing1@alt.icu
Requires-Python: >=3.7,<4.0
Classifier: Programming Language :: Python :: 3
Classifier: Programming Language :: Python :: 3.7
Classifier: Programming Language :: Python :: 3.8
Classifier: Programming Language :: Python :: 3.9
Classifier: Programming Language :: Python :: 3.10
Classifier: Programming Language :: Python :: 3.11
Classifier: Programming Language :: Python :: 3.12
Classifier: Programming Language :: Python :: 3.13
Requires-Dist: colorama (>=0.4.6,<0.5.0)
Requires-Dist: rich (>=13.4.1,<14.0.0)
Project-URL: Homepage, https://github.com/redthing1/minlog_python
